cadquery_freecad_import_plugin/__init__.py
cadquery_freecad_import_plugin/plugin.py
cadquery_freecad_import_plugin-1.0.0.dist-info/METADATA
cadquery_freecad_import_plugin-1.0.0.dist-info/WHEEL
cadquery_freecad_import_plugin-1.0.0.dist-info/licenses/LICENSE
cadquery_freecad_import_plugin-1.0.0.dist-info/RECORD
