Metadata-Version: 2.4
Name: cadquery_freecad_import_plugin
Version: 1.0.0
Summary: llows users to import FreeCAD models into CadQuery, and will apply parameters to the model if they are provided and the model is a parametric one.
Project-URL: Repository, https://github.com/jmwright/cadquery-freecad-import-plugin.git
Project-URL: Bug Tracker, https://github.com/jmwright/cadquery-freecad-import-plugin/issues
Author: Jeremy Wright
Maintainer: Jeremy Wright
License:                                  Apache License
License-File: LICENSE
Keywords: CAD,cadquery,design,engineering
Classifier: Development Status :: 4 - Beta
Classifier: Programming Language :: Python
Requires-Python: >=3.9
Requires-Dist: cadquery
Provides-Extra: dev
Requires-Dist: black; extra == 'dev'
Requires-Dist: pytest; extra == 'dev'
